kitten_art/__init__.py
kitten_art/art.py
kitten_art/data.py
kitten_art-0.1.0.dist-info/licenses/LICENSE
kitten_art-0.1.0.dist-info/METADATA
kitten_art-0.1.0.dist-info/WHEEL
kitten_art-0.1.0.dist-info/top_level.txt
kitten_art-0.1.0.dist-info/RECORD
